Virtual_Durability_Lab-1.17.dist-info/DESCRIPTION.rst
Virtual_Durability_Lab-1.17.dist-info/METADATA
Virtual_Durability_Lab-1.17.dist-info/RECORD
Virtual_Durability_Lab-1.17.dist-info/WHEEL
Virtual_Durability_Lab-1.17.dist-info/metadata.json
Virtual_Durability_Lab-1.17.dist-info/top_level.txt
duralab/DamageModel.py
duralab/DataTreatment.py
duralab/Sample.py
duralab/TestSample.py
duralab/TestingEfficiency.py
duralab/TestingEfficient.py
duralab/__init__.py
utils/DamageModel.py
utils/DataTreatment.py
utils/Sample.py
utils/TestSample.py
utils/TestingEfficient.py
utils/__init__.py
